agentfield/__init__.py
agentfield/agent.py
agentfield/agent_ai.py
agentfield/agent_cli.py
agentfield/agent_field_handler.py
agentfield/agent_mcp.py
agentfield/agent_registry.py
agentfield/agent_server.py
agentfield/agent_utils.py
agentfield/agent_workflow.py
agentfield/async_config.py
agentfield/async_execution_manager.py
agentfield/client.py
agentfield/connection_manager.py
agentfield/decorators.py
agentfield/did_manager.py
agentfield/dynamic_skills.py
agentfield/execution_context.py
agentfield/execution_state.py
agentfield/http_connection_manager.py
agentfield/litellm_adapters.py
agentfield/logger.py
agentfield/mcp_client.py
agentfield/mcp_manager.py
agentfield/mcp_stdio_bridge.py
agentfield/media_providers.py
agentfield/memory.py
agentfield/memory_events.py
agentfield/multimodal.py
agentfield/multimodal_response.py
agentfield/pydantic_utils.py
agentfield/rate_limiter.py
agentfield/result_cache.py
agentfield/router.py
agentfield/status.py
agentfield/types.py
agentfield/utils.py
agentfield/vc_generator.py
agentfield/vision.py
agentfield-0.1.39.dist-info/METADATA
agentfield-0.1.39.dist-info/WHEEL
agentfield-0.1.39.dist-info/top_level.txt
agentfield-0.1.39.dist-info/RECORD
